githubreportgenerator/__init__.py
githubreportgenerator/__main__.py
githubreportgenerator/models.py
githubreportgenerator/report.py
githubreportgenerator-0.0.4.dist-info/LICENSE
githubreportgenerator-0.0.4.dist-info/METADATA
githubreportgenerator-0.0.4.dist-info/WHEEL
githubreportgenerator-0.0.4.dist-info/entry_points.txt
githubreportgenerator-0.0.4.dist-info/top_level.txt
githubreportgenerator-0.0.4.dist-info/RECORD
