Metadata-Version: 2.1
Name: githubreportgenerator
Version: 0.0.4
Summary: A Dotnet Github Markdown Coverage Report Generator
Author: Joshua Cade Barber
Author-email: foundernq@gmail.com
Keywords: test coverage,dotnet report,cobertura,xplat,code coverage,github,github markdown
Classifier: Intended Audience :: Developers
Classifier: Programming Language :: Python :: 3
Classifier: Operating System :: MacOS :: MacOS X
Classifier: Operating System :: Microsoft :: Windows
Classifier: Operating System :: OS Independent
Classifier: Operating System :: POSIX
License-File: LICENSE
Requires-Dist: dacite
